aliyunsdkims/__init__.py
aliyunsdkims/endpoint.py
aliyunsdkims/request/__init__.py
aliyunsdkims/request/v20190815/AddClientIdToOIDCProviderRequest.py
aliyunsdkims/request/v20190815/AddFingerprintToOIDCProviderRequest.py
aliyunsdkims/request/v20190815/AddUserToGroupRequest.py
aliyunsdkims/request/v20190815/BindMFADeviceRequest.py
aliyunsdkims/request/v20190815/ChangePasswordRequest.py
aliyunsdkims/request/v20190815/CreateAccessKeyRequest.py
aliyunsdkims/request/v20190815/CreateAppSecretRequest.py
aliyunsdkims/request/v20190815/CreateApplicationRequest.py
aliyunsdkims/request/v20190815/CreateGroupRequest.py
aliyunsdkims/request/v20190815/CreateLoginProfileRequest.py
aliyunsdkims/request/v20190815/CreateOIDCProviderRequest.py
aliyunsdkims/request/v20190815/CreateSAMLProviderRequest.py
aliyunsdkims/request/v20190815/CreateUserRequest.py
aliyunsdkims/request/v20190815/CreateVirtualMFADeviceRequest.py
aliyunsdkims/request/v20190815/DeleteAccessKeyRequest.py
aliyunsdkims/request/v20190815/DeleteAppSecretRequest.py
aliyunsdkims/request/v20190815/DeleteApplicationRequest.py
aliyunsdkims/request/v20190815/DeleteGroupRequest.py
aliyunsdkims/request/v20190815/DeleteLoginProfileRequest.py
aliyunsdkims/request/v20190815/DeleteOIDCProviderRequest.py
aliyunsdkims/request/v20190815/DeleteSAMLProviderRequest.py
aliyunsdkims/request/v20190815/DeleteUserRequest.py
aliyunsdkims/request/v20190815/DeleteVirtualMFADeviceRequest.py
aliyunsdkims/request/v20190815/DisableVirtualMFARequest.py
aliyunsdkims/request/v20190815/GenerateCredentialReportRequest.py
aliyunsdkims/request/v20190815/GetAccessKeyLastUsedRequest.py
aliyunsdkims/request/v20190815/GetAccountMFAInfoRequest.py
aliyunsdkims/request/v20190815/GetAccountSecurityPracticeReportRequest.py
aliyunsdkims/request/v20190815/GetAccountSummaryRequest.py
aliyunsdkims/request/v20190815/GetAppSecretRequest.py
aliyunsdkims/request/v20190815/GetApplicationRequest.py
aliyunsdkims/request/v20190815/GetCredentialReportRequest.py
aliyun_python_sdk_ims-1.0.0.dist-info/LICENSE
aliyun_python_sdk_ims-1.0.0.dist-info/METADATA
aliyun_python_sdk_ims-1.0.0.dist-info/WHEEL
aliyun_python_sdk_ims-1.0.0.dist-info/top_level.txt
aliyun_python_sdk_ims-1.0.0.dist-info/RECORD
